cybro/__init__.py
cybro/cybro.py
cybro/exceptions.py
cybro/models.py
cybro-0.3.1.dist-info/LICENSE
cybro-0.3.1.dist-info/METADATA
cybro-0.3.1.dist-info/WHEEL
cybro-0.3.1.dist-info/RECORD
